MANIFEST.in
README.txt
setup.py
OASYS1_WISEr.egg-info/PKG-INFO
OASYS1_WISEr.egg-info/SOURCES.txt
OASYS1_WISEr.egg-info/dependency_links.txt
OASYS1_WISEr.egg-info/entry_points.txt
OASYS1_WISEr.egg-info/namespace_packages.txt
OASYS1_WISEr.egg-info/not-zip-safe
OASYS1_WISEr.egg-info/requires.txt
OASYS1_WISEr.egg-info/top_level.txt
orangecontrib/__init__.py
orangecontrib/wise2/__init__.py
orangecontrib/wise2/menu/__init__.py
orangecontrib/wise2/menu/ow_wise_tools_menu.py
orangecontrib/wise2/util/__init__.py
orangecontrib/wise2/util/wise_objects.py
orangecontrib/wise2/util/wise_util.py
orangecontrib/wise2/widgets/__init__.py
orangecontrib/wise2/widgets/gui/__init__.py
orangecontrib/wise2/widgets/gui/ow_optical_element.py
orangecontrib/wise2/widgets/gui/ow_wise_widget.py
orangecontrib/wise2/widgets/light_sources/__init__.py
orangecontrib/wise2/widgets/light_sources/ow_gaussian_source_1d.py
orangecontrib/wise2/widgets/light_sources/icons/gaussian_source_1d.png
orangecontrib/wise2/widgets/light_sources/icons/source.png
orangecontrib/wise2/widgets/optical_elements/__init__.py
orangecontrib/wise2/widgets/optical_elements/ow_detector.py
orangecontrib/wise2/widgets/optical_elements/ow_elliptic_mirror.py
orangecontrib/wise2/widgets/optical_elements/ow_plane_mirror.py
orangecontrib/wise2/widgets/optical_elements/icons/beam_stopper.png
orangecontrib/wise2/widgets/optical_elements/icons/ellipsoid_mirror.png
orangecontrib/wise2/widgets/optical_elements/icons/opticalElements.png
orangecontrib/wise2/widgets/optical_elements/icons/plane_mirror.png
orangecontrib/wise2/widgets/optical_elements/icons/screen.png
orangecontrib/wise2/widgets/optical_elements/icons/slit.png
orangecontrib/wise2/widgets/tools/__init__.py
orangecontrib/wise2/widgets/tools/dabam_height_profile.py
orangecontrib/wise2/widgets/tools/height_profile_simulator.py
orangecontrib/wise2/widgets/tools/ow_from_wofry_wavefront_1d.py
orangecontrib/wise2/widgets/tools/ow_wise_wavefront_to_wofry.py
orangecontrib/wise2/widgets/tools/icons/dabam.png
orangecontrib/wise2/widgets/tools/icons/from_wofry_wavefront_1d.png
orangecontrib/wise2/widgets/tools/icons/simulator.png
orangecontrib/wise2/widgets/tools/icons/tools.png
orangecontrib/wise2/widgets/tools/icons/wf_to_wofry_wavefront_1d.png