Metadata-Version: 1.1
Name: OASYS1-WISEr
Version: 1.0.7
Summary: WISEr in Python
Home-page: https://github.com/oasys-elettra-kit/WISE2
Author: Michele Manfredda, Lorenzo Raimondi, Luca Rebuffi
Author-email: luca.rebuffi@elettra.eu
License: GPLv3
Download-URL: https://github.com/oasys-elettra-kit/WISE2
Keywords: waveoptics,simulator,oasys1
Platform: UNKNOWN
Classifier: Development Status :: 4 - Beta
Classifier: Environment :: X11 Applications :: Qt
Classifier: Environment :: Console
Classifier: Environment :: Plugins
Classifier: Programming Language :: Python :: 3
Classifier: Intended Audience :: Science/Research
